{
	"name": "pf2eko",
	"title": "한글화（Pathfinder2e）",
	"description": "PF2e를 한국어로 하기 위한 Mod",
	"version": "0.01",
	"author": "Nibgnas",
	"languages": [
		{
			"lang": "ko",
			"system":"pf2e",
			"name": "한국어",
			"path": "lang/ko.json"
		}
	],
	"scripts": ["register-babele.js"],
  "styles" : ["main.css"],
  "packs": [],
  "dependencies": [
	  {
	"name": "babele",
	"manifest": "https://gitlab.com/riccisi/foundryvtt-babele/raw/master/module/module.json",
	"type": "module"
  	},
	{
	"name": "lib-wrapper",
	"manifest": "https://github.com/ruipin/fvtt-lib-wrapper/releases/latest/download/module.json",
	"type": "module"
	}
],
	"url" : "https://github.com/nibgnas/pf2eko",
	"download" : "https://github.com/nibgnas/pf2eko/latest/download/pf2eko.zip",
	"manifest" : "https://github.com/nibgnas/pf2eko/latest/download/system.json",
  "minimumCoreVersion": "0.9.0",
  "compatibleCoreVersion": "10"
}
